{"cacheElements":[],"cacheLayers":[],"cacheArtboardPaths":[],"undoStack":[[{"actionTypeRawValue":"proxy","methodArguments":[{"argumentTypeRawValue":4,"argumentGID":6}],"methodSignature":"removeWithElement:","targetGID":4}],[{"actionTypeRawValue":"proxy","methodArguments":[{"argumentTypeRawValue":4,"argumentEncodedJsonString":"{\"Argument\":{\"NSString\":\"Text\",\"NSAttributes\":{\"NSParagraphStyle\":{\"NSAllowsTighteningForTruncation\":1,\"$class\":\"NSMutableParagraphStyle\"},\"NSFont\":{\"UIFontMaximumPointSizeAfterScaling\":0,\"UIFontPointSizeForScaling\":0,\"UIFontDescriptor\":{\"UIFontDescriptorAttributes\":{\"NSFontSizeAttribute\":32,\"NSFontNameAttribute\":\"Helvetica\"},\"$class\":\"UIFontDescriptor\"},\"$class\":\"UIFont\",\"NSName\":\"Helvetica\",\"NSSize\":32,\"UIFontTraits\":0,\"UIFontPointSize\":32,\"UISystemFont\":false,\"UIFontName\":\"Helvetica\"}},\"$class\":\"NSAttributedString\"}}","argumentGID":0}],"methodSignature":"setText:","targetGID":6}],[{"actionTypeRawValue":"proxy","methodArguments":[{"argumentTypeRawValue":4,"argumentEncodedJsonString":"{\"Argument\":{\"WDSaturationKey\":0,\"WDHueKey\":0,\"WDAlphaKey\":1,\"WDBrightnessKey\":1,\"$class\":\"Vectornator.Color\"}}","argumentGID":0}],"methodSignature":"setFill:","targetGID":6}],[{"actionTypeRawValue":"proxy","methodArguments":[{"argumentTypeRawValue":4,"argumentEncodedJsonString":"{\"Argument\":{\"WDSaturationKey\":0.49297208867521369,\"WDHueKey\":0,\"WDAlphaKey\":1,\"WDBrightnessKey\":0.31872193113772451,\"$class\":\"Vectornator.Color\"}}","argumentGID":0}],"methodSignature":"setFill:","targetGID":6}],[{"actionTypeRawValue":"proxy","methodArguments":[{"argumentTypeRawValue":4,"argumentEncodedJsonString":"{\"Argument\":{\"WDSaturationKey\":0.49297208867521369,\"WDHueKey\":0,\"WDAlphaKey\":1,\"WDBrightnessKey\":0.31872193113772451,\"$class\":\"Vectornator.Color\"}}","argumentGID":0}],"methodSignature":"setFill:","targetGID":6}],[{"actionTypeRawValue":"proxy","methodArguments":[{"argumentTypeRawValue":4,"argumentEncodedJsonString":"{\"Argument\":{\"WDSaturationKey\":0.49297208867521369,\"WDHueKey\":0.64134174585342407,\"WDAlphaKey\":1,\"WDBrightnessKey\":0.31872193113772451,\"$class\":\"Vectornator.Color\"}}","argumentGID":0}],"methodSignature":"setFill:","targetGID":6}],[{"actionTypeRawValue":"proxy","methodArguments":[{"argumentTypeRawValue":2,"argumentEncodedJsonString":"{\"Argument\":32}","argumentGID":0}],"methodSignature":"setFontSize:","targetGID":6}],[{"actionTypeRawValue":"proxy","methodArguments":[{"argumentTypeRawValue":6,"argumentEncodedJsonString":"{\"Argument\":\"[1, -0, -0, 1, -986.21949288468966, -278.65014567770385]\"}","argumentGID":0},{"argumentTypeRawValue":5,"argumentEncodedJsonString":"{\"Argument\":[6]}","argumentGID":0},{"argumentTypeRawValue":4,"argumentEncodedJsonString":"{\"Argument\":{\"UpdateAngleAfterTransformTransformOptionKey\":1,\"TransformingNodesTransformOptionKey\":false}}","argumentGID":0}],"methodSignature":"applyTransform:forElements:options:","targetGID":0}],[{"actionTypeRawValue":"proxy","methodArguments":[{"argumentTypeRawValue":6,"argumentEncodedJsonString":"{\"Argument\":\"[1, -0, -0, 1, 391.01074852252225, -0]\"}","argumentGID":0},{"argumentTypeRawValue":5,"argumentEncodedJsonString":"{\"Argument\":[6]}","argumentGID":0},{"argumentTypeRawValue":4,"argumentEncodedJsonString":"{\"Argument\":{\"UpdateAngleAfterTransformTransformOptionKey\":1,\"TransformingNodesTransformOptionKey\":false}}","argumentGID":0}],"methodSignature":"applyTransform:forElements:options:","targetGID":0}],[{"actionTypeRawValue":"proxy","methodArguments":[{"argumentTypeRawValue":6,"argumentEncodedJsonString":"{\"Argument\":\"[1, -0, -0, 1, 24.614236675246048, -0]\"}","argumentGID":0},{"argumentTypeRawValue":5,"argumentEncodedJsonString":"{\"Argument\":[6]}","argumentGID":0},{"argumentTypeRawValue":4,"argumentEncodedJsonString":"{\"Argument\":{\"UpdateAngleAfterTransformTransformOptionKey\":1,\"TransformingNodesTransformOptionKey\":false}}","argumentGID":0}],"methodSignature":"applyTransform:forElements:options:","targetGID":0}],[{"actionTypeRawValue":"proxy","methodArguments":[{"argumentTypeRawValue":6,"argumentEncodedJsonString":"{\"Argument\":\"[1, -0, -0, 1, 249.41324319198748, 437.53564313112645]\"}","argumentGID":0},{"argumentTypeRawValue":5,"argumentEncodedJsonString":"{\"Argument\":[6]}","argumentGID":0},{"argumentTypeRawValue":4,"argumentEncodedJsonString":"{\"Argument\":{\"UpdateAngleAfterTransformTransformOptionKey\":1,\"TransformingNodesTransformOptionKey\":false}}","argumentGID":0}],"methodSignature":"applyTransform:forElements:options:","targetGID":0}],[{"actionTypeRawValue":"proxy","methodArguments":[{"argumentTypeRawValue":4,"argumentGID":9}],"methodSignature":"removeWithElement:","targetGID":4}],[{"actionTypeRawValue":"proxy","methodArguments":[{"argumentTypeRawValue":6,"argumentEncodedJsonString":"{\"Argument\":\"[1.3018711411699944, -0, -0, 1.2095227294994233, 5.0251634791177553, 3.881954782213128]\"}","argumentGID":0},{"argumentTypeRawValue":5,"argumentEncodedJsonString":"{\"Argument\":[9]}","argumentGID":0},{"argumentTypeRawValue":4,"argumentEncodedJsonString":"{\"Argument\":{\"UpdateAngleAfterTransformTransformOptionKey\":1,\"TransformingNodesTransformOptionKey\":false}}","argumentGID":0}],"methodSignature":"applyTransform:forElements:options:","targetGID":0}],[{"actionTypeRawValue":"proxy","methodArguments":[{"argumentTypeRawValue":6,"argumentEncodedJsonString":"{\"Argument\":\"[1, -0, -0, 1, -198.75193794231711, -109.20318594481969]\"}","argumentGID":0},{"argumentTypeRawValue":5,"argumentEncodedJsonString":"{\"Argument\":[6]}","argumentGID":0},{"argumentTypeRawValue":4,"argumentEncodedJsonString":"{\"Argument\":{\"UpdateAngleAfterTransformTransformOptionKey\":1,\"TransformingNodesTransformOptionKey\":false}}","argumentGID":0}],"methodSignature":"applyTransform:forElements:options:","targetGID":0}],[{"actionTypeRawValue":"proxy","methodArguments":[{"argumentTypeRawValue":0,"argumentEncodedJsonString":"{\"Argument\":0}","argumentGID":0},{"argumentTypeRawValue":0,"argumentEncodedJsonString":"{\"Argument\":1}","argumentGID":0}],"methodSignature":"swapElementAtIndex:with:","targetGID":4}],[{"actionTypeRawValue":"proxy","methodArguments":[{"argumentTypeRawValue":6,"argumentEncodedJsonString":"{\"Argument\":\"[1, -0, -0, 1, 482.31974423326324, -39.736772443720156]\"}","argumentGID":0},{"argumentTypeRawValue":5,"argumentEncodedJsonString":"{\"Argument\":[6]}","argumentGID":0},{"argumentTypeRawValue":4,"argumentEncodedJsonString":"{\"Argument\":{\"UpdateAngleAfterTransformTransformOptionKey\":1,\"TransformingNodesTransformOptionKey\":false}}","argumentGID":0}],"methodSignature":"applyTransform:forElements:options:","targetGID":0}],[{"actionTypeRawValue":"proxy","methodArguments":[{"argumentTypeRawValue":6,"argumentEncodedJsonString":"{\"Argument\":\"[1, 0, 0, 1, 110.21460108728866, 149.836626462461]\"}","argumentGID":0}],"methodSignature":"setTransform:","targetGID":6},{"actionTypeRawValue":"proxy","methodArguments":[{"argumentTypeRawValue":2,"argumentEncodedJsonString":"{\"Argument\":291.00750732421875}","argumentGID":0}],"methodSignature":"setWidth:","targetGID":6},{"actionTypeRawValue":"proxy","methodArguments":[{"argumentTypeRawValue":2,"argumentEncodedJsonString":"{\"Argument\":174.08258056640625}","argumentGID":0}],"methodSignature":"setHeight:","targetGID":6}],[{"actionTypeRawValue":"proxy","methodArguments":[{"argumentTypeRawValue":6,"argumentEncodedJsonString":"{\"Argument\":\"[1, -0, -0, 1, 68.224841968553903, 90.547195945341031]\"}","argumentGID":0},{"argumentTypeRawValue":5,"argumentEncodedJsonString":"{\"Argument\":[6]}","argumentGID":0},{"argumentTypeRawValue":4,"argumentEncodedJsonString":"{\"Argument\":{\"UpdateAngleAfterTransformTransformOptionKey\":1,\"TransformingNodesTransformOptionKey\":false}}","argumentGID":0}],"methodSignature":"applyTransform:forElements:options:","targetGID":0}],[{"actionTypeRawValue":"proxy","methodArguments":[{"argumentTypeRawValue":2,"argumentEncodedJsonString":"{\"Argument\":64}","argumentGID":0}],"methodSignature":"setFontSize:","targetGID":6}],[{"actionTypeRawValue":"proxy","methodArguments":[{"argumentTypeRawValue":6,"argumentEncodedJsonString":"{\"Argument\":\"[1, 0, 0, 1, 41.989759118734753, 59.289430517119968]\"}","argumentGID":0}],"methodSignature":"setTransform:","targetGID":6},{"actionTypeRawValue":"proxy","methodArguments":[{"argumentTypeRawValue":2,"argumentEncodedJsonString":"{\"Argument\":161.92237854003906}","argumentGID":0}],"methodSignature":"setWidth:","targetGID":6},{"actionTypeRawValue":"proxy","methodArguments":[{"argumentTypeRawValue":2,"argumentEncodedJsonString":"{\"Argument\":61.365402221679688}","argumentGID":0}],"methodSignature":"setHeight:","targetGID":6}],[{"actionTypeRawValue":"proxy","methodArguments":[{"argumentTypeRawValue":6,"argumentEncodedJsonString":"{\"Argument\":\"[1, -0, -0, 1, 3.0504407627296928, -48.583374825749132]\"}","argumentGID":0},{"argumentTypeRawValue":5,"argumentEncodedJsonString":"{\"Argument\":[6]}","argumentGID":0},{"argumentTypeRawValue":4,"argumentEncodedJsonString":"{\"Argument\":{\"UpdateAngleAfterTransformTransformOptionKey\":1,\"TransformingNodesTransformOptionKey\":false}}","argumentGID":0}],"methodSignature":"applyTransform:forElements:options:","targetGID":0}],[{"actionTypeRawValue":"proxy","methodArguments":[{"argumentTypeRawValue":6,"argumentEncodedJsonString":"{\"Argument\":\"[1, 0, 0, 1, 38.93931835600506, 107.8728053428691]\"}","argumentGID":0}],"methodSignature":"setTransform:","targetGID":6},{"actionTypeRawValue":"proxy","methodArguments":[{"argumentTypeRawValue":2,"argumentEncodedJsonString":"{\"Argument\":345.619873046875}","argumentGID":0}],"methodSignature":"setWidth:","targetGID":6},{"actionTypeRawValue":"proxy","methodArguments":[{"argumentTypeRawValue":2,"argumentEncodedJsonString":"{\"Argument\":224.95137023925781}","argumentGID":0}],"methodSignature":"setHeight:","targetGID":6}],[{"actionTypeRawValue":"proxy","methodArguments":[{"argumentTypeRawValue":4,"argumentEncodedJsonString":"{\"Argument\":\"Helvetica\"}","argumentGID":0}],"methodSignature":"setFontName:","targetGID":6}],[{"actionTypeRawValue":"proxy","methodArguments":[{"argumentTypeRawValue":4,"argumentEncodedJsonString":"{\"Argument\":\"Helvetica-LightOblique\"}","argumentGID":0}],"methodSignature":"setFontName:","targetGID":6}],[{"actionTypeRawValue":"proxy","methodArguments":[{"argumentTypeRawValue":6,"argumentEncodedJsonString":"{\"Argument\":\"[1, -0, -0, 1, 0.55108919199153661, -28.095823688180928]\"}","argumentGID":0},{"argumentTypeRawValue":5,"argumentEncodedJsonString":"{\"Argument\":[6]}","argumentGID":0},{"argumentTypeRawValue":4,"argumentEncodedJsonString":"{\"Argument\":{\"UpdateAngleAfterTransformTransformOptionKey\":1,\"TransformingNodesTransformOptionKey\":false}}","argumentGID":0}],"methodSignature":"applyTransform:forElements:options:","targetGID":0}],[{"actionTypeRawValue":"proxy","methodArguments":[{"argumentTypeRawValue":6,"argumentEncodedJsonString":"{\"Argument\":\"[1, -0, -0, 1, 28.501036329351223, 2.4669345594445531]\"}","argumentGID":0},{"argumentTypeRawValue":5,"argumentEncodedJsonString":"{\"Argument\":[6]}","argumentGID":0},{"argumentTypeRawValue":4,"argumentEncodedJsonString":"{\"Argument\":{\"UpdateAngleAfterTransformTransformOptionKey\":1,\"TransformingNodesTransformOptionKey\":false}}","argumentGID":0}],"methodSignature":"applyTransform:forElements:options:","targetGID":0}],[{"actionTypeRawValue":"proxy","methodArguments":[{"argumentTypeRawValue":6,"argumentEncodedJsonString":"{\"Argument\":\"[1, 0, 0, 1, 9.8871928346623008, 133.50169447160548]\"}","argumentGID":0}],"methodSignature":"setTransform:","targetGID":6},{"actionTypeRawValue":"proxy","methodArguments":[{"argumentTypeRawValue":2,"argumentEncodedJsonString":"{\"Argument\":324.2764892578125}","argumentGID":0}],"methodSignature":"setWidth:","targetGID":6},{"actionTypeRawValue":"proxy","methodArguments":[{"argumentTypeRawValue":2,"argumentEncodedJsonString":"{\"Argument\":162.21797180175781}","argumentGID":0}],"methodSignature":"setHeight:","targetGID":6}],[{"actionTypeRawValue":"proxy","methodArguments":[{"argumentTypeRawValue":4,"argumentEncodedJsonString":"{\"Argument\":{\"NSString\":\"VCAI\",\"NSAttributeInfo\":{\"$data\":\"AQADAQ==\",\"$class\":\"NSMutableData\"},\"NSAttributes\":[{\"NSKern\":0,\"com.linearity.vn.kerning\":0,\"NSFont\":{\"NSSize\":128,\"NSfFlags\":80,\"NSDescriptor\":{\"UIFontDescriptorAttributes\":{\"NSFontSizeAttribute\":128,\"NSFontNameAttribute\":\"Helvetica-BoldOblique\"},\"$class\":\"UIFontDescriptor\"},\"NSName\":\"Helvetica-BoldOblique\",\"$class\":\"NSFont\"},\"NSParagraphStyle\":{\"NSAllowsTighteningForTruncation\":1,\"$class\":\"NSMutableParagraphStyle\"}},{\"NSParagraphStyle\":{\"NSAllowsTighteningForTruncation\":1,\"$class\":\"NSMutableParagraphStyle\"},\"com.linearity.vn.tracking\":0,\"com.linearity.vn.kerning\":0,\"NSFont\":{\"$alias\":\"Argument.NSAttributes.0.NSFont\"},\"NSKern\":0}],\"$class\":\"NSAttributedString\"}}","argumentGID":0}],"methodSignature":"setText:","targetGID":6}],[{"actionTypeRawValue":"proxy","methodArguments":[{"argumentTypeRawValue":4,"argumentGID":10}],"methodSignature":"removeWithElement:","targetGID":4}],[{"actionTypeRawValue":"proxy","methodArguments":[{"argumentTypeRawValue":4,"argumentEncodedJsonString":"{\"Argument\":{\"NSString\":\"Text\",\"NSAttributes\":{\"NSParagraphStyle\":{\"NSAllowsTighteningForTruncation\":1,\"$class\":\"NSMutableParagraphStyle\"},\"NSFont\":{\"NSSize\":128,\"NSfFlags\":80,\"NSDescriptor\":{\"UIFontDescriptorAttributes\":{\"NSFontSizeAttribute\":128,\"NSFontNameAttribute\":\"Helvetica-BoldOblique\"},\"$class\":\"UIFontDescriptor\"},\"NSName\":\"Helvetica-BoldOblique\",\"$class\":\"NSFont\"}},\"$class\":\"NSAttributedString\"}}","argumentGID":0}],"methodSignature":"setText:","targetGID":10}],[{"actionTypeRawValue":"proxy","methodArguments":[{"argumentTypeRawValue":2,"argumentEncodedJsonString":"{\"Argument\":128}","argumentGID":0}],"methodSignature":"setFontSize:","targetGID":10}],[{"actionTypeRawValue":"proxy","methodArguments":[{"argumentTypeRawValue":6,"argumentEncodedJsonString":"{\"Argument\":\"[1, -0, -0, 1, -187.97328168718832, 216.06262197311048]\"}","argumentGID":0},{"argumentTypeRawValue":5,"argumentEncodedJsonString":"{\"Argument\":[10]}","argumentGID":0},{"argumentTypeRawValue":4,"argumentEncodedJsonString":"{\"Argument\":{\"UpdateAngleAfterTransformTransformOptionKey\":1,\"TransformingNodesTransformOptionKey\":false}}","argumentGID":0}],"methodSignature":"applyTransform:forElements:options:","targetGID":0}],[{"actionTypeRawValue":"proxy","methodArguments":[{"argumentTypeRawValue":6,"argumentEncodedJsonString":"{\"Argument\":\"[1, 0, 0, 1, 265.57902509539144, 297.00659189407702]\"}","argumentGID":0}],"methodSignature":"setTransform:","targetGID":10},{"actionTypeRawValue":"proxy","methodArguments":[{"argumentTypeRawValue":2,"argumentEncodedJsonString":"{\"Argument\":192.67373657226562}","argumentGID":0}],"methodSignature":"setWidth:","targetGID":10},{"actionTypeRawValue":"proxy","methodArguments":[{"argumentTypeRawValue":2,"argumentEncodedJsonString":"{\"Argument\":64.37371826171875}","argumentGID":0}],"methodSignature":"setHeight:","targetGID":10}],[{"actionTypeRawValue":"proxy","methodArguments":[{"argumentTypeRawValue":2,"argumentEncodedJsonString":"{\"Argument\":128}","argumentGID":0}],"methodSignature":"setFontSize:","targetGID":6}],[{"actionTypeRawValue":"proxy","methodArguments":[{"argumentTypeRawValue":6,"argumentEncodedJsonString":"{\"Argument\":\"[1, -0, -0, 1, 49.883296978623378, 77.048752442677397]\"}","argumentGID":0},{"argumentTypeRawValue":5,"argumentEncodedJsonString":"{\"Argument\":[6]}","argumentGID":0},{"argumentTypeRawValue":4,"argumentEncodedJsonString":"{\"Argument\":{\"UpdateAngleAfterTransformTransformOptionKey\":1,\"TransformingNodesTransformOptionKey\":false}}","argumentGID":0}],"methodSignature":"applyTransform:forElements:options:","targetGID":0}],[{"actionTypeRawValue":"proxy","methodArguments":[{"argumentTypeRawValue":6,"argumentEncodedJsonString":"{\"Argument\":\"[1, 0, 0, 1, -39.996104143961077, 56.452942028928078]\"}","argumentGID":0}],"methodSignature":"setTransform:","targetGID":6},{"actionTypeRawValue":"proxy","methodArguments":[{"argumentTypeRawValue":2,"argumentEncodedJsonString":"{\"Argument\":366.09445190429688}","argumentGID":0}],"methodSignature":"setWidth:","targetGID":6},{"actionTypeRawValue":"proxy","methodArguments":[{"argumentTypeRawValue":2,"argumentEncodedJsonString":"{\"Argument\":200.34036254882812}","argumentGID":0}],"methodSignature":"setHeight:","targetGID":6}],[{"actionTypeRawValue":"proxy","methodArguments":[{"argumentTypeRawValue":6,"argumentEncodedJsonString":"{\"Argument\":\"[1, 0, 0, 1, 5.3835955630701733, 56.452942028928078]\"}","argumentGID":0}],"methodSignature":"setTransform:","targetGID":6},{"actionTypeRawValue":"proxy","methodArguments":[{"argumentTypeRawValue":2,"argumentEncodedJsonString":"{\"Argument\":320.71475219726562}","argumentGID":0}],"methodSignature":"setWidth:","targetGID":6},{"actionTypeRawValue":"proxy","methodArguments":[{"argumentTypeRawValue":2,"argumentEncodedJsonString":"{\"Argument\":200.34036254882812}","argumentGID":0}],"methodSignature":"setHeight:","targetGID":6}],[{"actionTypeRawValue":"proxy","methodArguments":[{"argumentTypeRawValue":0,"argumentEncodedJsonString":"{\"Argument\":0}","argumentGID":0}],"methodSignature":"setAlignment:","targetGID":6}],[{"actionTypeRawValue":"proxy","methodArguments":[{"argumentTypeRawValue":2,"argumentEncodedJsonString":"{\"Argument\":256}","argumentGID":0}],"methodSignature":"setFontSize:","targetGID":6}],[{"actionTypeRawValue":"proxy","methodArguments":[{"argumentTypeRawValue":6,"argumentEncodedJsonString":"{\"Argument\":\"[1, 0, 0, 1, 5.3835955630701733, 56.452942028928078]\"}","argumentGID":0}],"methodSignature":"setTransform:","targetGID":6},{"actionTypeRawValue":"proxy","methodArguments":[{"argumentTypeRawValue":2,"argumentEncodedJsonString":"{\"Argument\":381.56765747070312}","argumentGID":0}],"methodSignature":"setWidth:","targetGID":6},{"actionTypeRawValue":"proxy","methodArguments":[{"argumentTypeRawValue":2,"argumentEncodedJsonString":"{\"Argument\":295.59451293945312}","argumentGID":0}],"methodSignature":"setHeight:","targetGID":6}],[{"actionTypeRawValue":"proxy","methodArguments":[{"argumentTypeRawValue":6,"argumentEncodedJsonString":"{\"Argument\":\"[1, 0, 0, 1, 5.3835955630701733, 107.30226459059821]\"}","argumentGID":0}],"methodSignature":"setTransform:","targetGID":6},{"actionTypeRawValue":"proxy","methodArguments":[{"argumentTypeRawValue":2,"argumentEncodedJsonString":"{\"Argument\":316.22470092773438}","argumentGID":0}],"methodSignature":"setWidth:","targetGID":6},{"actionTypeRawValue":"proxy","methodArguments":[{"argumentTypeRawValue":2,"argumentEncodedJsonString":"{\"Argument\":244.74519348144531}","argumentGID":0}],"methodSignature":"setHeight:","targetGID":6}],[{"actionTypeRawValue":"proxy","methodArguments":[{"argumentTypeRawValue":6,"argumentEncodedJsonString":"{\"Argument\":\"[1, -0, -0, 1, 2.7781378678632791, -2.8202799825449745]\"}","argumentGID":0},{"argumentTypeRawValue":5,"argumentEncodedJsonString":"{\"Argument\":[6]}","argumentGID":0},{"argumentTypeRawValue":4,"argumentEncodedJsonString":"{\"Argument\":{\"UpdateAngleAfterTransformTransformOptionKey\":1,\"TransformingNodesTransformOptionKey\":false}}","argumentGID":0}],"methodSignature":"applyTransform:forElements:options:","targetGID":0}],[{"actionTypeRawValue":"proxy","methodArguments":[{"argumentTypeRawValue":6,"argumentEncodedJsonString":"{\"Argument\":\"[1, -0, -0, 1, -44.489106299364835, 39.704355432426439]\"}","argumentGID":0},{"argumentTypeRawValue":5,"argumentEncodedJsonString":"{\"Argument\":[10]}","argumentGID":0},{"argumentTypeRawValue":4,"argumentEncodedJsonString":"{\"Argument\":{\"UpdateAngleAfterTransformTransformOptionKey\":1,\"TransformingNodesTransformOptionKey\":false}}","argumentGID":0}],"methodSignature":"applyTransform:forElements:options:","targetGID":0}],[{"actionTypeRawValue":"proxy","methodArguments":[{"argumentTypeRawValue":2,"argumentEncodedJsonString":"{\"Argument\":32}","argumentGID":0}],"methodSignature":"setFontSize:","targetGID":10}],[{"actionTypeRawValue":"proxy","methodArguments":[{"argumentTypeRawValue":6,"argumentEncodedJsonString":"{\"Argument\":\"[1, -0, -0, 1, 13.193723596503531, 1.5916752545167583]\"}","argumentGID":0},{"argumentTypeRawValue":5,"argumentEncodedJsonString":"{\"Argument\":[6]}","argumentGID":0},{"argumentTypeRawValue":4,"argumentEncodedJsonString":"{\"Argument\":{\"UpdateAngleAfterTransformTransformOptionKey\":1,\"TransformingNodesTransformOptionKey\":false}}","argumentGID":0}],"methodSignature":"applyTransform:forElements:options:","targetGID":0}],[{"actionTypeRawValue":"proxy","methodArguments":[{"argumentTypeRawValue":6,"argumentEncodedJsonString":"{\"Argument\":\"[1, 0, 0, 1, 310.06813139475628, 257.30223646165058]\"}","argumentGID":0}],"methodSignature":"setTransform:","targetGID":10},{"actionTypeRawValue":"proxy","methodArguments":[{"argumentTypeRawValue":2,"argumentEncodedJsonString":"{\"Argument\":54.473545074462891}","argumentGID":0}],"methodSignature":"setWidth:","targetGID":10},{"actionTypeRawValue":"proxy","methodArguments":[{"argumentTypeRawValue":2,"argumentEncodedJsonString":"{\"Argument\":39.4580078125}","argumentGID":0}],"methodSignature":"setHeight:","targetGID":10}],[{"actionTypeRawValue":"proxy","methodArguments":[{"argumentTypeRawValue":6,"argumentEncodedJsonString":"{\"Argument\":\"[1, -0, -0, 1, 13.021913436647424, 24.416492906355018]\"}","argumentGID":0},{"argumentTypeRawValue":5,"argumentEncodedJsonString":"{\"Argument\":[10]}","argumentGID":0},{"argumentTypeRawValue":4,"argumentEncodedJsonString":"{\"Argument\":{\"UpdateAngleAfterTransformTransformOptionKey\":1,\"TransformingNodesTransformOptionKey\":false}}","argumentGID":0}],"methodSignature":"applyTransform:forElements:options:","targetGID":0}],[{"actionTypeRawValue":"proxy","methodArguments":[{"argumentTypeRawValue":6,"argumentEncodedJsonString":"{\"Argument\":\"[1, -0, -0, 1, 15.297587629459542, 33.969786134584979]\"}","argumentGID":0},{"argumentTypeRawValue":5,"argumentEncodedJsonString":"{\"Argument\":[6]}","argumentGID":0},{"argumentTypeRawValue":4,"argumentEncodedJsonString":"{\"Argument\":{\"UpdateAngleAfterTransformTransformOptionKey\":1,\"TransformingNodesTransformOptionKey\":false}}","argumentGID":0}],"methodSignature":"applyTransform:forElements:options:","targetGID":0}],[{"actionTypeRawValue":"proxy","methodArguments":[{"argumentTypeRawValue":2,"argumentEncodedJsonString":"{\"Argument\":192}","argumentGID":0}],"methodSignature":"setFontSize:","targetGID":6}],[{"actionTypeRawValue":"proxy","methodArguments":[{"argumentTypeRawValue":6,"argumentEncodedJsonString":"{\"Argument\":\"[1, 0, 0, 1, -0.88908839403742945, 74.561083184041451]\"}","argumentGID":0}],"methodSignature":"setTransform:","targetGID":6},{"actionTypeRawValue":"proxy","methodArguments":[{"argumentTypeRawValue":2,"argumentEncodedJsonString":"{\"Argument\":291.22793579101562}","argumentGID":0}],"methodSignature":"setWidth:","targetGID":6},{"actionTypeRawValue":"proxy","methodArguments":[{"argumentTypeRawValue":2,"argumentEncodedJsonString":"{\"Argument\":202.06172180175781}","argumentGID":0}],"methodSignature":"setHeight:","targetGID":6}],[{"actionTypeRawValue":"proxy","methodArguments":[{"argumentTypeRawValue":6,"argumentEncodedJsonString":"{\"Argument\":\"[1, -0, -0, 1, 9.5824685383942665, -8.9438534159099277]\"}","argumentGID":0},{"argumentTypeRawValue":5,"argumentEncodedJsonString":"{\"Argument\":[6]}","argumentGID":0},{"argumentTypeRawValue":4,"argumentEncodedJsonString":"{\"Argument\":{\"UpdateAngleAfterTransformTransformOptionKey\":1,\"TransformingNodesTransformOptionKey\":false}}","argumentGID":0}],"methodSignature":"applyTransform:forElements:options:","targetGID":0}],[{"actionTypeRawValue":"proxy","methodArguments":[{"argumentTypeRawValue":0,"argumentEncodedJsonString":"{\"Argument\":1}","argumentGID":0}],"methodSignature":"setAlignment:","targetGID":6}],[{"actionTypeRawValue":"proxy","methodArguments":[{"argumentTypeRawValue":6,"argumentEncodedJsonString":"{\"Argument\":\"[1, -0, -0, 1, 10.892115794656519, 6.4282933395249984]\"}","argumentGID":0},{"argumentTypeRawValue":5,"argumentEncodedJsonString":"{\"Argument\":[6]}","argumentGID":0},{"argumentTypeRawValue":4,"argumentEncodedJsonString":"{\"Argument\":{\"UpdateAngleAfterTransformTransformOptionKey\":1,\"TransformingNodesTransformOptionKey\":false}}","argumentGID":0}],"methodSignature":"applyTransform:forElements:options:","targetGID":0}],[{"actionTypeRawValue":"proxy","methodArguments":[{"argumentTypeRawValue":6,"argumentEncodedJsonString":"{\"Argument\":\"[1, -0, -0, 1, 6.4088431327487569, 23.252722200914036]\"}","argumentGID":0},{"argumentTypeRawValue":5,"argumentEncodedJsonString":"{\"Argument\":[6]}","argumentGID":0},{"argumentTypeRawValue":4,"argumentEncodedJsonString":"{\"Argument\":{\"UpdateAngleAfterTransformTransformOptionKey\":1,\"TransformingNodesTransformOptionKey\":false}}","argumentGID":0}],"methodSignature":"applyTransform:forElements:options:","targetGID":0}],[{"actionTypeRawValue":"proxy","methodArguments":[{"argumentTypeRawValue":6,"argumentEncodedJsonString":"{\"Argument\":\"[1, -0, -0, 1, -20.542660056767318, 24.811980444137248]\"}","argumentGID":0},{"argumentTypeRawValue":5,"argumentEncodedJsonString":"{\"Argument\":[10]}","argumentGID":0},{"argumentTypeRawValue":4,"argumentEncodedJsonString":"{\"Argument\":{\"UpdateAngleAfterTransformTransformOptionKey\":1,\"TransformingNodesTransformOptionKey\":false}}","argumentGID":0}],"methodSignature":"applyTransform:forElements:options:","targetGID":0}],[{"actionTypeRawValue":"proxy","methodArguments":[{"argumentTypeRawValue":2,"argumentEncodedJsonString":"{\"Argument\":216}","argumentGID":0}],"methodSignature":"setFontSize:","targetGID":6}],[{"actionTypeRawValue":"proxy","methodArguments":[{"argumentTypeRawValue":6,"argumentEncodedJsonString":"{\"Argument\":\"[1, -0, -0, 1, 0.0032417011293546238, -0.68075723716606262]\"}","argumentGID":0},{"argumentTypeRawValue":5,"argumentEncodedJsonString":"{\"Argument\":[6]}","argumentGID":0},{"argumentTypeRawValue":4,"argumentEncodedJsonString":"{\"Argument\":{\"UpdateAngleAfterTransformTransformOptionKey\":1,\"TransformingNodesTransformOptionKey\":false}}","argumentGID":0}],"methodSignature":"applyTransform:forElements:options:","targetGID":0}],[{"actionTypeRawValue":"proxy","methodArguments":[{"argumentTypeRawValue":2,"argumentEncodedJsonString":"{\"Argument\":64}","argumentGID":0}],"methodSignature":"setFontSize:","targetGID":10}],[{"actionTypeRawValue":"proxy","methodArguments":[{"argumentTypeRawValue":2,"argumentEncodedJsonString":"{\"Argument\":86}","argumentGID":0}],"methodSignature":"setFontSize:","targetGID":10}],[{"actionTypeRawValue":"proxy","methodArguments":[{"argumentTypeRawValue":6,"argumentEncodedJsonString":"{\"Argument\":\"[1, -0, -0, 1, 9.0540712543082691, -4.609699005952848]\"}","argumentGID":0},{"argumentTypeRawValue":5,"argumentEncodedJsonString":"{\"Argument\":[10]}","argumentGID":0},{"argumentTypeRawValue":4,"argumentEncodedJsonString":"{\"Argument\":{\"UpdateAngleAfterTransformTransformOptionKey\":1,\"TransformingNodesTransformOptionKey\":false}}","argumentGID":0}],"methodSignature":"applyTransform:forElements:options:","targetGID":0}],[{"actionTypeRawValue":"proxy","methodArguments":[{"argumentTypeRawValue":6,"argumentEncodedJsonString":"{\"Argument\":\"[1, 0, 0, 1, 308.5348067605679, 212.68346211711116]\"}","argumentGID":0}],"methodSignature":"setTransform:","targetGID":10},{"actionTypeRawValue":"proxy","methodArguments":[{"argumentTypeRawValue":2,"argumentEncodedJsonString":"{\"Argument\":74.104995727539062}","argumentGID":0}],"methodSignature":"setWidth:","targetGID":10},{"actionTypeRawValue":"proxy","methodArguments":[{"argumentTypeRawValue":2,"argumentEncodedJsonString":"{\"Argument\":66.944389343261719}","argumentGID":0}],"methodSignature":"setHeight:","targetGID":10}],[{"actionTypeRawValue":"proxy","methodArguments":[{"argumentTypeRawValue":6,"argumentEncodedJsonString":"{\"Argument\":\"[1, -0, -0, 1, 0.34037861858303131, 1.6856845872682698]\"}","argumentGID":0},{"argumentTypeRawValue":5,"argumentEncodedJsonString":"{\"Argument\":[6]}","argumentGID":0},{"argumentTypeRawValue":4,"argumentEncodedJsonString":"{\"Argument\":{\"UpdateAngleAfterTransformTransformOptionKey\":1,\"TransformingNodesTransformOptionKey\":false}}","argumentGID":0}],"methodSignature":"applyTransform:forElements:options:","targetGID":0}],[{"actionTypeRawValue":"proxy","methodArguments":[{"argumentTypeRawValue":6,"argumentEncodedJsonString":"{\"Argument\":\"[1, 0, 0, 1, -28.116136179549358, 52.818993709410137]\"}","argumentGID":0}],"methodSignature":"setTransform:","targetGID":6},{"actionTypeRawValue":"proxy","methodArguments":[{"argumentTypeRawValue":2,"argumentEncodedJsonString":"{\"Argument\":337.73660278320312}","argumentGID":0}],"methodSignature":"setWidth:","targetGID":6},{"actionTypeRawValue":"proxy","methodArguments":[{"argumentTypeRawValue":2,"argumentEncodedJsonString":"{\"Argument\":235.35073852539062}","argumentGID":0}],"methodSignature":"setHeight:","targetGID":6}],[{"actionTypeRawValue":"proxy","methodArguments":[{"argumentTypeRawValue":6,"argumentEncodedJsonString":"{\"Argument\":\"[1, -0, -0, 1, -1.6824428861388014, 10.227567063137258]\"}","argumentGID":0},{"argumentTypeRawValue":5,"argumentEncodedJsonString":"{\"Argument\":[10]}","argumentGID":0},{"argumentTypeRawValue":4,"argumentEncodedJsonString":"{\"Argument\":{\"UpdateAngleAfterTransformTransformOptionKey\":1,\"TransformingNodesTransformOptionKey\":false}}","argumentGID":0}],"methodSignature":"applyTransform:forElements:options:","targetGID":0}],[{"actionTypeRawValue":"proxy","methodArguments":[{"argumentTypeRawValue":6,"argumentEncodedJsonString":"{\"Argument\":\"[1, -0, -0, 1, -2.6970953396292145, -6.1041232265887402]\"}","argumentGID":0},{"argumentTypeRawValue":5,"argumentEncodedJsonString":"{\"Argument\":[6]}","argumentGID":0},{"argumentTypeRawValue":4,"argumentEncodedJsonString":"{\"Argument\":{\"UpdateAngleAfterTransformTransformOptionKey\":1,\"TransformingNodesTransformOptionKey\":false}}","argumentGID":0}],"methodSignature":"applyTransform:forElements:options:","targetGID":0}]],"isGroupingUndo":false,"currentUndoGroup":[],"currentRedoGroup":[],"isGroupingRedo":false,"redoStack":[[{"actionTypeRawValue":"proxy","methodArguments":[{"argumentTypeRawValue":4,"argumentEncodedJsonString":"{\"Argument\":\"SFPro-Thin\"}","argumentGID":0}],"methodSignature":"setFontName:","targetGID":6}]],"nextGID":14}